use_mysql/__init__.py
use_mysql-0.0.2.dist-info/METADATA
use_mysql-0.0.2.dist-info/WHEEL
use_mysql-0.0.2.dist-info/RECORD
